nba_on_court/__init__.py
nba_on_court/matchups.py
nba_on_court/nba_on_court.py
nba_on_court-0.2.0.dist-info/LICENSE
nba_on_court-0.2.0.dist-info/METADATA
nba_on_court-0.2.0.dist-info/WHEEL
nba_on_court-0.2.0.dist-info/RECORD
