Metadata-Version: 2.1
Name: nba-on-court
Version: 0.2.0
Summary: Adding players on court to play-by-play data
Home-page: https://github.com/shufinskiy/nba-on-court
License: MIT
Keywords: api,basketball,data,nba,sports,stats
Author: Vladislav Shufinsky
Author-email: shufinsky.90210@gmail.com
Maintainer: Vladislav Shufinsky
Maintainer-email: shufinsky.90210@gmail.com
Requires-Python: >=3.8,<4.0
Classifier: Intended Audience :: Developers
Classifier: Intended Audience :: Science/Research
Classifier: License :: OSI Approved :: MIT License
Classifier: Operating System :: OS Independent
Classifier: Programming Language :: Python :: 3
Classifier: Programming Language :: Python :: 3.8
Classifier: Programming Language :: Python :: 3.9
Classifier: Programming Language :: Python :: 3.10
Classifier: Programming Language :: Python :: 3.11
Classifier: Topic :: Software Development
Requires-Dist: nba-api (>=1.1.8,<2.0.0)
Requires-Dist: numpy (>=1.0.0,<2.0.0)
Requires-Dist: pandas (>=1.3.5)
Requires-Dist: polyleven (>=0.8,<0.9)
Requires-Dist: requests
Project-URL: Bug Tracker, https://github.com/shufinskiy/nba-on-court/issues
Project-URL: Documentation, https://github.com/shufinskiy/nba-on-court/blob/master/README.md
Project-URL: Repository, https://github.com/shufinskiy/nba-on-court
